Metadata-Version: 1.1
Name: stocal
Version: 1.2
Summary: simple rule-based stochastic simulation
Home-page: https://github.com/harfel/
Author: Harold Fellermann
Author-email: harold.fellermann@newcastle.ac.uk
License: MIT
Platform: UNKNOWN
Classifier: Development Status :: 3 - Alpha
Classifier: License :: OSI Approved :: MIT License
Classifier: Programming Language :: Python :: 2.7
Classifier: Programming Language :: Python :: 3.5
Classifier: Topic :: Scientific/Engineering :: Chemistry
Classifier: Topic :: Scientific/Engineering :: Mathematics
Classifier: Topic :: Scientific/Engineering :: Physics
